chuk_mcp_ios/__init__.py
chuk_mcp_ios/main.py
chuk_mcp_ios/cli/__init__.py
chuk_mcp_ios/cli/main.py
chuk_mcp_ios/core/__init__.py
chuk_mcp_ios/core/app_manager.py
chuk_mcp_ios/core/base.py
chuk_mcp_ios/core/device_manager.py
chuk_mcp_ios/core/logger_manager.py
chuk_mcp_ios/core/media_manager.py
chuk_mcp_ios/core/session_manager.py
chuk_mcp_ios/core/ui_controller.py
chuk_mcp_ios/core/utilities_manager.py
chuk_mcp_ios/devices/__init__.py
chuk_mcp_ios/devices/detector.py
chuk_mcp_ios/devices/real_device.py
chuk_mcp_ios/devices/simulator.py
chuk_mcp_ios/mcp/__init__.py
chuk_mcp_ios/mcp/main.py
chuk_mcp_ios/mcp/models.py
chuk_mcp_ios/mcp/tools.py
chuk_mcp_ios-0.1.5.dist-info/METADATA
chuk_mcp_ios-0.1.5.dist-info/WHEEL
chuk_mcp_ios-0.1.5.dist-info/entry_points.txt
chuk_mcp_ios-0.1.5.dist-info/top_level.txt
chuk_mcp_ios-0.1.5.dist-info/RECORD
