Metadata-Version: 2.4
Name: chuk-mcp-ios
Version: 0.1.5
Summary: iOS Device Control MCP Server - Comprehensive iOS automation and testing
Author-email: Chris Hay <chris@chrishayuk.com>
License: MIT
Project-URL: Homepage, https://github.com/chrishayuk/chuk-mcp-ios
Project-URL: Documentation, https://github.com/chrishayuk/chuk-mcp-ios/blob/main/README.md
Project-URL: Repository, https://github.com/chrishayuk/chuk-mcp-ios
Project-URL: Issues, https://github.com/chrishayuk/chuk-mcp-ios/issues
Keywords: ios,simulator,automation,testing,mcp,device-control
Classifier: Development Status :: 4 - Beta
Classifier: Intended Audience :: Developers
Classifier: License :: OSI Approved :: MIT License
Classifier: Operating System :: MacOS
Classifier: Programming Language :: Python :: 3
Classifier: Programming Language :: Python :: 3.11
Classifier: Programming Language :: Python :: 3.12
Classifier: Topic :: Software Development :: Testing
Classifier: Topic :: System :: Emulators
Requires-Python: >=3.11
Requires-Dist: beautifulsoup4>=4.13.4
Requires-Dist: chuk-mcp-runtime>=0.3
Requires-Dist: pillow>=11.2.1
Requires-Dist: pydantic>=2.11.5
Requires-Dist: requests>=2.32.3
Requires-Dist: click>=8.0.0
Provides-Extra: dev
Requires-Dist: pytest>=7.0; extra == "dev"
Requires-Dist: pytest-cov>=4.0; extra == "dev"
Requires-Dist: ruff>=0.1.0; extra == "dev"
Requires-Dist: mypy>=1.0; extra == "dev"
Provides-Extra: real-device
Requires-Dist: fb-idb>=1.1.7; extra == "real-device"
